LICENSE.txt
MANIFEST.in
README.md
setup.cfg
setup.py
BankStatementAnalysis/BankStatementAnalysis.pyd
BankStatementAnalysis/__init__.py
BankStatementAnalysis.egg-info/PKG-INFO
BankStatementAnalysis.egg-info/SOURCES.txt
BankStatementAnalysis.egg-info/dependency_links.txt
BankStatementAnalysis.egg-info/top_level.txt
BankStatementAnalysis/icons/Forword_picture.png
BankStatementAnalysis/icons/__init__.py
BankStatementAnalysis/icons/back_picture.png
BankStatementAnalysis/icons/home.png
BankStatementAnalysis/icons/logo.png
BankStatementAnalysis/icons/refresh.png
BankStatementAnalysis/icons/stop.png