Metadata-Version: 2.1
Name: BankStatementAnalysis
Version: 0.1.3
Summary: 银行流水核查
Home-page: https://alidocs.dingtalk.com/i/p/4oJRz0VRJyvmLZMydy0mV7WvjQn7MG89
Author: zhaojianhua liangyilong
Author-email: 17891967090@163.com
Classifier: Programming Language :: Python
Requires-Python: >=3.8
License-File: LICENSE.txt
